<!-- converted from XMB to XML -->

<protounitsounddef>
	<protounit name="SCivet">
		<soundtype name="Select">
			<soundset name="LuwakSelect"/>
		</soundtype>
		<soundtype name="Grunt">
			<soundset name="LuwakGrunt"/>
		</soundtype>
		<soundtype name="Death">
			<soundset name="LuwakDeath"/>
		</soundtype>
		<soundtype name="Creation">
			<soundset name="SettlerBirth"/>
		</soundtype>
		<soundtype name="Acknowledge">
			<soundset name="LuwakMove"/>
		</soundtype>
	</protounit>
</protounitsounddef>